{
  "accounts": {
    "account{0}": "0xfD08836eeE6242092a9c869237a8d122275b024A"
  },
  "linkReferences": {},
  "transactions": [
    {
      "timestamp": 1750233362714,
      "record": {
        "value": "50000000000000000",
        "inputs": "(uint256,uint256,string,string,uint256,bytes)",
        "parameters": [
          "9",
          "10000000",
          "0xoopopdopo",
          "coding",
          "100000000",
          "0x00030100110100000000000000000000000000030d40"
        ],
        "name": "raiseDispute",
        "type": "function",
        "to": "created{undefined}",
        "from": "account{0}"
      }
    },
    {
      "timestamp": 1750233394187,
      "record": {
        "value": "50000000000000008",
        "inputs": "(uint256,uint256,string,string,uint256,bytes)",
        "parameters": [
          "9",
          "10000000",
          "0xoopopdopo",
          "coding",
          "100000000",
          "0x00030100110100000000000000000000000000030d40"
        ],
        "name": "raiseDispute",
        "type": "function",
        "to": "created{undefined}",
        "from": "account{0}"
      }
    },
    {
      "timestamp": 1750233442407,
      "record": {
        "value": "50000000000000008",
        "inputs": "(uint256,uint256,string,string,uint256,bytes)",
        "parameters": [
          "10",
          "10000000",
          "0xoopopdopo",
          "coding",
          "100000000",
          "0x00030100110100000000000000000000000000030d40"
        ],
        "name": "raiseDispute",
        "type": "function",
        "to": "created{undefined}",
        "from": "account{0}"
      }
    },
    {
      "timestamp": 1750233467001,
      "record": {
        "value": "50000000000000008",
        "inputs": "(uint256,uint256,string,string,uint256,bytes)",
        "parameters": [
          "10",
          "10000000",
          "0xoopopdopo",
          "coding",
          "100000000",
          "0x00030100110100000000000000000000000000030d40"
        ],
        "name": "raiseDispute",
        "type": "function",
        "to": "created{undefined}",
        "from": "account{0}"
      }
    },
    {
      "timestamp": 1750233680837,
      "record": {
        "value": "50000000000000008",
        "inputs": "(uint256,uint256,string,string,uint256,bytes)",
        "parameters": [
          "10",
          "10000000",
          "0xoopopdopo",
          "coding",
          "100000000",
          "0x0003010011010000000000000000000000000493e0"
        ],
        "name": "raiseDispute",
        "type": "function",
        "to": "created{undefined}",
        "from": "account{0}"
      }
    },
    {
      "timestamp": 1750233848040,
      "record": {
        "value": "50000000000000008",
        "inputs": "(address,uint256)",
        "parameters": [
          "0xC44B60Aae862E5Be7c67750206436DAAAD6c9266",
          "1000000000000"
        ],
        "name": "approve",
        "type": "function",
        "to": "created{undefined}",
        "from": "account{0}"
      }
    },
    {
      "timestamp": 1750233858269,
      "record": {
        "value": "0",
        "inputs": "(address,uint256)",
        "parameters": [
          "0xC44B60Aae862E5Be7c67750206436DAAAD6c9266",
          "1000000000000"
        ],
        "name": "approve",
        "type": "function",
        "to": "created{undefined}",
        "from": "account{0}"
      }
    },
    {
      "timestamp": 1750233864243,
      "record": {
        "value": "0",
        "inputs": "(address,uint256)",
        "parameters": [
          "0xC44B60Aae862E5Be7c67750206436DAAAD6c9266",
          "1000000000000"
        ],
        "name": "approve",
        "type": "function",
        "to": "created{undefined}",
        "from": "account{0}"
      }
    }
  ],
  "abis": {}
}